odoo/addons/purchase_order_secondary_unit/README.rst
odoo/addons/purchase_order_secondary_unit/__init__.py
odoo/addons/purchase_order_secondary_unit/__manifest__.py
odoo/addons/purchase_order_secondary_unit/i18n/de.po
odoo/addons/purchase_order_secondary_unit/i18n/es.po
odoo/addons/purchase_order_secondary_unit/i18n/fr.po
odoo/addons/purchase_order_secondary_unit/i18n/hr.po
odoo/addons/purchase_order_secondary_unit/i18n/it.po
odoo/addons/purchase_order_secondary_unit/i18n/ja.po
odoo/addons/purchase_order_secondary_unit/i18n/pt_BR.po
odoo/addons/purchase_order_secondary_unit/i18n/purchase_order_secondary_unit.pot
odoo/addons/purchase_order_secondary_unit/models/__init__.py
odoo/addons/purchase_order_secondary_unit/models/product_product.py
odoo/addons/purchase_order_secondary_unit/models/product_template.py
odoo/addons/purchase_order_secondary_unit/models/purchase_order.py
odoo/addons/purchase_order_secondary_unit/readme/CONTRIBUTORS.md
odoo/addons/purchase_order_secondary_unit/readme/DESCRIPTION.md
odoo/addons/purchase_order_secondary_unit/readme/USAGE.md
odoo/addons/purchase_order_secondary_unit/reports/purchase_order_templates.xml
odoo/addons/purchase_order_secondary_unit/reports/purchase_quotation_templates.xml
odoo/addons/purchase_order_secondary_unit/static/description/icon.png
odoo/addons/purchase_order_secondary_unit/static/description/index.html
odoo/addons/purchase_order_secondary_unit/tests/__init__.py
odoo/addons/purchase_order_secondary_unit/tests/test_purchase_order_secondary_unit.py
odoo/addons/purchase_order_secondary_unit/views/product_views.xml
odoo/addons/purchase_order_secondary_unit/views/purchase_order_views.xml
odoo_addon_purchase_order_secondary_unit-18.0.1.0.1.dist-info/METADATA
odoo_addon_purchase_order_secondary_unit-18.0.1.0.1.dist-info/WHEEL
odoo_addon_purchase_order_secondary_unit-18.0.1.0.1.dist-info/top_level.txt
odoo_addon_purchase_order_secondary_unit-18.0.1.0.1.dist-info/RECORD
